odoo8_addon_mrp_lock_lot-8.0.3.0.0.99.dev3-nspkg.pth
odoo_addons/mrp_lock_lot/README.rst
odoo_addons/mrp_lock_lot/__init__.py
odoo_addons/mrp_lock_lot/__openerp__.py
odoo_addons/mrp_lock_lot/i18n/de.po
odoo_addons/mrp_lock_lot/i18n/es.po
odoo_addons/mrp_lock_lot/i18n/es_MX.po
odoo_addons/mrp_lock_lot/i18n/fr.po
odoo_addons/mrp_lock_lot/i18n/gl.po
odoo_addons/mrp_lock_lot/i18n/hr.po
odoo_addons/mrp_lock_lot/i18n/it.po
odoo_addons/mrp_lock_lot/i18n/mrp_lock_lot.pot
odoo_addons/mrp_lock_lot/i18n/pt_BR.po
odoo_addons/mrp_lock_lot/i18n/ro.po
odoo_addons/mrp_lock_lot/i18n/sl.po
odoo_addons/mrp_lock_lot/i18n/tr.po
odoo_addons/mrp_lock_lot/i18n/vi_VN.po
odoo_addons/mrp_lock_lot/i18n/zh_CN.po
odoo_addons/mrp_lock_lot/models/__init__.py
odoo_addons/mrp_lock_lot/models/mrp_production.py
odoo_addons/mrp_lock_lot/static/description/icon.png
odoo_addons/mrp_lock_lot/tests/__init__.py
odoo_addons/mrp_lock_lot/tests/test_mrp_lock_lot.py
odoo_addons/mrp_lock_lot/wizard/__init__.py
odoo_addons/mrp_lock_lot/wizard/mrp_product_produce.py
odoo_addons/mrp_lock_lot/wizard/mrp_product_produce_view.xml
odoo8_addon_mrp_lock_lot-8.0.3.0.0.99.dev3.dist-info/METADATA
odoo8_addon_mrp_lock_lot-8.0.3.0.0.99.dev3.dist-info/WHEEL
odoo8_addon_mrp_lock_lot-8.0.3.0.0.99.dev3.dist-info/namespace_packages.txt
odoo8_addon_mrp_lock_lot-8.0.3.0.0.99.dev3.dist-info/top_level.txt
odoo8_addon_mrp_lock_lot-8.0.3.0.0.99.dev3.dist-info/RECORD
