Metadata-Version: 2.1
Name: odoo8-addon-mrp-lock-lot
Version: 8.0.3.0.0.99.dev3
Summary: MRP Lock Lot
Home-page: http://www.odoomrp.com
Author: OdooMRP team,Avanzosc,Serv. Tecnol. Avanzados - Pedro M. Baeza,Odoo Community Association (OCA)
Author-email: support@odoo-community.org
License: AGPL-3
Platform: UNKNOWN
Classifier: Programming Language :: Python
Classifier: Framework :: Odoo
Classifier: License :: OSI Approved :: GNU Affero General Public License v3
Requires-Python: ~=2.7
Requires-Dist: odoo8-addon-stock-lock-lot
Requires-Dist: odoo (<9.0a,>=8.0a)
